myrt_desk_api/__init__.py
myrt_desk_api/domain.py
myrt_desk_api/version.py
myrt_desk_api/backlight/__init__.py
myrt_desk_api/backlight/domain.py
myrt_desk_api/backlight/firmware.py
myrt_desk_api/backlight/types.py
myrt_desk_api/cli/__init__.py
myrt_desk_api/cli/assert_val.py
myrt_desk_api/cli/convert.py
myrt_desk_api/cli/progress.py
myrt_desk_api/legs/__init__.py
myrt_desk_api/legs/domain.py
myrt_desk_api/legs/types.py
myrt_desk_api/system/__init__.py
myrt_desk_api/system/domain.py
myrt_desk_api/system/ota.py
myrt_desk_api/system/types.py
myrt_desk_api/transport/__init__.py
myrt_desk_api/transport/bytes.py
myrt_desk_api/transport/constants.py
myrt_desk_api/transport/persistent_stream.py
myrt_desk_api/transport/ping.py
myrt_desk_api/transport/socket_stream.py
myrt_desk_api/transport/types.py
myrt_desk_api-1.0.7.data/scripts/myrt_desk
myrt_desk_api-1.0.7.dist-info/LICENSE
myrt_desk_api-1.0.7.dist-info/METADATA
myrt_desk_api-1.0.7.dist-info/WHEEL
myrt_desk_api-1.0.7.dist-info/top_level.txt
myrt_desk_api-1.0.7.dist-info/RECORD
