Metadata-Version: 2.1
Name: myrt_desk_api
Version: 1.0.7
Summary: Library for controlling smart bulbs that are controlled by the DoIT protocol
Author: Mikhael Khrustik
Classifier: Programming Language :: Python :: 3
Classifier: License :: OSI Approved :: MIT License
Requires-Python: >=3.7
License-File: LICENSE
Requires-Dist: asyncio-datagram ==1.4.0
Requires-Dist: arrrgs ==3.1.0
Requires-Dist: typing-extensions ==4.11.0
Requires-Dist: async-timeout ==4.0.3
